chartDL/__init__.py
chartDL/database.py
chartDL/dataset.py
chartDL/indicator.py
chartDL/preprocess.py
chartDL/utils/__init__.py
chartDL/utils/csv.py
chartDL/utils/time.py
chartDL/utils/visual.py
chart_data_dl-0.1.1.dist-info/licenses/LICENSE
chart_data_dl-0.1.1.dist-info/METADATA
chart_data_dl-0.1.1.dist-info/WHEEL
chart_data_dl-0.1.1.dist-info/top_level.txt
chart_data_dl-0.1.1.dist-info/RECORD
