Metadata-Version: 2.4
Name: chart-data-dl
Version: 0.1.1
Summary: chartDL: Market chart data preprocessing for machine learning and deep learning with multi-timeframe dataset support.
Home-page: https://github.com/mehranESB/ohlcv-chart-tools.git
Author: Mehran ESMAILYBAJEGANI
Author-email: mehranesmaily907@gmail.com
License: MIT
Keywords: chartDL,finance,trading,machine learning,deep learning,OHLCV,technical analysis
Classifier: Development Status :: 3 - Alpha
Classifier: Intended Audience :: Developers
Classifier: Intended Audience :: Science/Research
Classifier: Topic :: Scientific/Engineering :: Artificial Intelligence
Classifier: Topic :: Software Development :: Libraries :: Python Modules
Classifier: Topic :: Office/Business :: Financial
Classifier: Topic :: Utilities
Classifier: License :: OSI Approved :: MIT License
Classifier: Programming Language :: Python :: 3
Classifier: Programming Language :: Python :: 3.8
Classifier: Programming Language :: Python :: 3.9
Classifier: Programming Language :: Python :: 3.10
Requires-Python: >=3.8
License-File: LICENSE
Requires-Dist: pandas
Requires-Dist: numpy
Requires-Dist: matplotlib
Dynamic: license-file
